email_service/__init__.py
email_service/main.py
email_service/version.py
email_service/core/config.py
email_service/core/service_container.py
email_service/data/__init__.py
email_service/domain/__init__.py
email_service/domain/consumer.py
email_service/domain/email_schema.py
email_service/domain/email_server.py
email_service/domain/email_service.py
email_service/domain/publisher.py
email_service/endpoints/__init__.py
py_email_service-0.0.1.dist-info/LICENSE
py_email_service-0.0.1.dist-info/METADATA
py_email_service-0.0.1.dist-info/WHEEL
py_email_service-0.0.1.dist-info/entry_points.txt
py_email_service-0.0.1.dist-info/top_level.txt
py_email_service-0.0.1.dist-info/RECORD
